{
	"code": 200,
	"message": "Success",
	"userStats": [
		{
			"seasonId": 21,
			"userNum": 124728,
			"matchingMode": 3,
			"matchingTeamMode": 3,
			"mmr": 6416,
			"nickname": "\ub9e5\ub3c4",
			"rank": 11,
			"rankSize": 114482,
			"totalGames": 222,
			"totalWins": 42,
			"totalTeamKills": 2106,
			"totalDeaths": 473,
			"escapeCount": 3,
			"rankPercent": 0.0,
			"averageRank": 4.08,
			"averageKills": 4.37,
			"averageAssistants": 3.47,
			"averageHunts": 40.36,
			"top1": 0.19,
			"top2": 0.32,
			"top3": 0.46,
			"top5": 0.68,
			"top7": 0.9,
			"characterStats": [
				{
					"characterCode": 22,
					"totalGames": 182,
					"usages": 182,
					"maxKillings": 14,
					"top3": 84,
					"wins": 34,
					"top3Rate": 0,
					"averageRank": 4
				},
				{
					"characterCode": 56,
					"totalGames": 25,
					"usages": 25,
					"maxKillings": 12,
					"top3": 12,
					"wins": 5,
					"top3Rate": 0,
					"averageRank": 4
				},
				{
					"characterCode": 11,
					"totalGames": 8,
					"usages": 8,
					"maxKillings": 11,
					"top3": 4,
					"wins": 2,
					"top3Rate": 0,
					"averageRank": 3
				}
			]
		}
	]
}